plyr/__init__.py
plyr/__version__.py
plyr/base.cpython-310-darwin.so
python_plyr-0.8.1.dist-info/LICENSE
python_plyr-0.8.1.dist-info/METADATA
python_plyr-0.8.1.dist-info/WHEEL
python_plyr-0.8.1.dist-info/top_level.txt
python_plyr-0.8.1.dist-info/RECORD
