Metadata-Version: 2.1
Name: python-plyr
Version: 0.8.1
Summary: Mapping tools for nested containers.
Home-page: https://github.com/ivannz/plyr
Author: Ivan Nazarov
Author-email: ivannnnz@gmail.com
License: MIT License
Requires-Python: >=3.7
License-File: LICENSE
